azure_auth/__init__.py
azure_auth/apps.py
azure_auth/backends.py
azure_auth/decorators.py
azure_auth/exceptions.py
azure_auth/handlers.py
azure_auth/middleware.py
azure_auth/tests/__init__.py
azure_auth/tests/conftest.py
azure_auth/tests/misc.py
azure_auth/tests/settings.py
azure_auth/tests/test_decorators.py
azure_auth/tests/test_handler.py
azure_auth/tests/test_middleware.py
azure_auth/tests/test_views.py
azure_auth/tests/urls.py
azure_auth/urls.py
azure_auth/utils.py
azure_auth/views.py
django_azure_auth-2.5.0.dist-info/METADATA
django_azure_auth-2.5.0.dist-info/WHEEL
django_azure_auth-2.5.0.dist-info/licenses/LICENSE
django_azure_auth-2.5.0.dist-info/RECORD
