Metadata-Version: 2.4
Name: django-azure-auth
Version: 2.5.0
Summary: A simple Django app for user authentication with Azure Active Directory/Entra ID.
License: MIT
License-File: LICENSE
Keywords: django,azure,authentication,microsoft,entra
Author: Weird Sheep Labs
Author-email: info@weirdsheeplabs.com
Requires-Python: >=3.8,<4.0
Classifier: Development Status :: 5 - Production/Stable
Classifier: Framework :: Django
Classifier: Intended Audience :: Information Technology
Classifier: License :: OSI Approved :: MIT License
Classifier: Programming Language :: Python :: 3
Classifier: Programming Language :: Python :: 3.8
Classifier: Programming Language :: Python :: 3.9
Classifier: Programming Language :: Python :: 3.10
Classifier: Programming Language :: Python :: 3.11
Classifier: Programming Language :: Python :: 3.12
Classifier: Programming Language :: Python :: 3.13
Classifier: Programming Language :: Python :: 3.14
Requires-Dist: Django (>=3.2)
Requires-Dist: msal (>=1.18.0,<2.0.0)
Project-URL: Homepage, https://github.com/Weird-Sheep-Labs/django-azure-auth
